cms_qe
cms_qe_analytical
cms_qe_auth
cms_qe_breadcrumb
cms_qe_i18n
cms_qe_menu
cms_qe_newsletter
cms_qe_plugins
cms_qe_table
cms_qe_test
cms_qe_video
